README
setup.py
metonym/__init__.py
metonym.egg-info/PKG-INFO
metonym.egg-info/SOURCES.txt
metonym.egg-info/dependency_links.txt
metonym.egg-info/requires.txt
metonym.egg-info/top_level.txt
scripts/create_wordnet_graph
test/__init__.py
test/test_metonym.py