Metadata-Version: 1.0
Name: metonym
Version: 0.2
Summary: Getting better path similarity measures from wordnet by graphing the synsets
Home-page: UNKNOWN
Author: Sharmila Gopirajan Sivakumar
Author-email: siva.sharmi@gmail.com
License: UNKNOWN
Platform: UNKNOWN
